AUTHORS
INSTALL
LICENSE
MANIFEST.in
NEWS
README.md
codecov.yml
conftest.py
pytest.ini
setup.cfg
setup.py
tox.ini
Scrapy_Team.egg-info/PKG-INFO
Scrapy_Team.egg-info/SOURCES.txt
Scrapy_Team.egg-info/dependency_links.txt
Scrapy_Team.egg-info/entry_points.txt
Scrapy_Team.egg-info/not-zip-safe
Scrapy_Team.egg-info/requires.txt
Scrapy_Team.egg-info/top_level.txt
docs/Makefile
docs/README.rst
docs/conf.py
docs/conftest.py
docs/contributing.rst
docs/faq.rst
docs/index.rst
docs/news.rst
docs/requirements.txt
docs/versioning.rst
docs/_ext/scrapydocs.py
docs/_static/custom.css
docs/intro/examples.rst
docs/intro/install.rst
docs/intro/overview.rst
docs/intro/tutorial.rst
docs/topics/api.rst
docs/topics/architecture.rst
docs/topics/asyncio.rst
docs/topics/autothrottle.rst
docs/topics/benchmarking.rst
docs/topics/broad-crawls.rst
docs/topics/commands.rst
docs/topics/contracts.rst
docs/topics/coroutines.rst
docs/topics/debug.rst
docs/topics/deploy.rst
docs/topics/developer-tools.rst
docs/topics/djangoitem.rst
docs/topics/downloader-middleware.rst
docs/topics/dynamic-content.rst
docs/topics/email.rst
docs/topics/exceptions.rst
docs/topics/exporters.rst
docs/topics/extensions.rst
docs/topics/feed-exports.rst
docs/topics/item-pipeline.rst
docs/topics/items.rst
docs/topics/jobs.rst
docs/topics/leaks.rst
docs/topics/link-extractors.rst
docs/topics/loaders.rst
docs/topics/logging.rst
docs/topics/media-pipeline.rst
docs/topics/practices.rst
docs/topics/request-response.rst
docs/topics/scheduler.rst
docs/topics/scrapyd.rst
docs/topics/selectors.rst
docs/topics/settings.rst
docs/topics/shell.rst
docs/topics/signals.rst
docs/topics/spider-middleware.rst
docs/topics/spiders.rst
docs/topics/stats.rst
docs/topics/telnetconsole.rst
docs/topics/webservice.rst
docs/topics/_images/inspector_01.png
docs/topics/_images/network_01.png
docs/topics/_images/network_02.png
docs/topics/_images/network_03.png
docs/topics/_images/scrapy_architecture.odg
docs/topics/_images/scrapy_architecture.png
docs/topics/_images/scrapy_architecture_02.png
docs/utils/linkfix.py
extras/coverage-report.sh
extras/qps-bench-server.py
extras/qpsclient.py
extras/scrapy.1
extras/scrapy_bash_completion
extras/scrapy_zsh_completion
scrapy/VERSION
scrapy/__init__.py
