Metadata-Version: 2.1
Name: Scrapy-Team
Version: 1.3.1
Summary: Based on scrapy framework, combined with common component tools
Home-page: https://scrapy.org
Author: buliqioqiolibusdo
Author-email: dingyeran@163.com
License: BSD
Project-URL: Documentation, https://docs.scrapy.org/
Project-URL: Source, https://github.com/buliqioqiolibusdo/scrapyer
Project-URL: Tracker, https://github.com/buliqioqiolibusdo/scrapyer/issues
Platform: UNKNOWN
Requires-Python: >=3.6
